geogals/__init__.py
geogals/geogals.py
geogals/hyperleda_table.py
geogals/meta_data.py
geogals/projection.py
geogals/phangs/Z_diags.py
geogals/phangs/__init__.py
geogals/phangs/phangs.py
geogals-0.1.8.dist-info/licenses/LICENSE
geogals-0.1.8.dist-info/METADATA
geogals-0.1.8.dist-info/WHEEL
geogals-0.1.8.dist-info/top_level.txt
geogals-0.1.8.dist-info/RECORD
