Metadata-Version: 2.4
Name: geogals
Version: 0.1.8
Summary: A publicly available repository for using geostatistical methods on real and simulated galaxy data.
Author-email: Benjamin Metha <methab@student.unimelb.edu.au>
Maintainer-email: Benjamin Metha <methab@student.unimelb.edu.au>
License: MIT
Project-URL: bugs, https://github.com/astrobenji/geogals/issues
Project-URL: changelog, https://github.com/astrobenji/geogals/blob/master/changelog.md
Project-URL: homepage, https://github.com/astrobenji/geogals
Classifier: Programming Language :: Python :: 3
Classifier: License :: OSI Approved :: MIT License
Classifier: Operating System :: OS Independent
Requires-Python: >=3.7
License-File: LICENSE
Provides-Extra: dev
Requires-Dist: coverage; extra == "dev"
Requires-Dist: mypy; extra == "dev"
Requires-Dist: pytest; extra == "dev"
Requires-Dist: ruff; extra == "dev"
Dynamic: license-file
